sushy/__init__.py
sushy/auth.py
sushy/connector.py
sushy/exceptions.py
sushy/main.py
sushy/taskmonitor.py
sushy/utils.py
sushy/oem/__init__.py
sushy/oem/dell/__init__.py
sushy/oem/dell/asynchronous.py
sushy/oem/dell/constants.py
sushy/oem/dell/utils.py
sushy/oem/dell/resources/__init__.py
sushy/oem/dell/resources/attributes.py
sushy/oem/dell/resources/manager/__init__.py
sushy/oem/dell/resources/manager/constants.py
sushy/oem/dell/resources/manager/idrac_card_service.py
sushy/oem/dell/resources/manager/job_collection.py
sushy/oem/dell/resources/manager/job_service.py
sushy/oem/dell/resources/manager/lifecycle_service.py
sushy/oem/dell/resources/manager/manager.py
sushy/oem/dell/resources/system/constants.py
sushy/oem/dell/resources/system/raid_service.py
sushy/oem/dell/resources/system/system.py
sushy/oem/dell/resources/system/storage/constants.py
sushy/oem/dell/resources/system/storage/controller.py
sushy/oem/dell/resources/taskservice/constants.py
sushy/oem/dell/resources/taskservice/task.py
sushy/resources/__init__.py
sushy/resources/base.py
sushy/resources/common.py
sushy/resources/constants.py
sushy/resources/ipaddresses.py
sushy/resources/settings.py
sushy/resources/certificateservice/__init__.py
sushy/resources/certificateservice/certificate.py
sushy/resources/certificateservice/certificateservice.py
sushy/resources/certificateservice/constants.py
sushy/resources/chassis/__init__.py
sushy/resources/chassis/chassis.py
sushy/resources/chassis/constants.py
sushy/resources/chassis/power/__init__.py
sushy/resources/chassis/power/constants.py
sushy/resources/chassis/power/power.py
sushy/resources/chassis/thermal/__init__.py
sushy/resources/chassis/thermal/constants.py
sushy/resources/chassis/thermal/thermal.py
sushy/resources/compositionservice/__init__.py
sushy/resources/compositionservice/compositionservice.py
sushy/resources/compositionservice/constants.py
sushy/resources/compositionservice/resourceblock.py
sushy/resources/compositionservice/resourcezone.py
sushy-5.8.0.dist-info/AUTHORS
sushy-5.8.0.dist-info/LICENSE
sushy-5.8.0.dist-info/METADATA
sushy-5.8.0.dist-info/WHEEL
sushy-5.8.0.dist-info/entry_points.txt
sushy-5.8.0.dist-info/pbr.json
sushy-5.8.0.dist-info/top_level.txt
sushy-5.8.0.dist-info/RECORD
