Metadata-Version: 2.1
Name: sushy
Version: 5.8.0
Summary: Sushy is a small Python library to communicate with Redfish based systems
Home-page: https://docs.openstack.org/sushy/latest/
Author: OpenStack
Author-email: openstack-discuss@lists.openstack.org
Classifier: Environment :: OpenStack
Classifier: Intended Audience :: Information Technology
Classifier: Intended Audience :: System Administrators
Classifier: License :: OSI Approved :: Apache Software License
Classifier: Operating System :: POSIX :: Linux
Classifier: Programming Language :: Python
Classifier: Programming Language :: Python :: Implementation :: CPython
Classifier: Programming Language :: Python :: 3 :: Only
Classifier: Programming Language :: Python :: 3
Classifier: Programming Language :: Python :: 3.10
Classifier: Programming Language :: Python :: 3.11
Classifier: Programming Language :: Python :: 3.12
Requires-Python: >=3.10
License-File: LICENSE
License-File: AUTHORS
Requires-Dist: pbr >=6.0.0
Requires-Dist: requests >=2.14.2
Requires-Dist: python-dateutil >=2.7.0
Requires-Dist: stevedore >=1.29.0
